trinitypython/__init__.py
trinitypython/account/__init__.py
trinitypython/account/reconcile.py
trinitypython/datautils/__init__.py
trinitypython/datautils/jsonutil.py
trinitypython/datautils/table.py
trinitypython/debugutils/__init__.py
trinitypython/debugutils/curpos.py
trinitypython/debugutils/find.py
trinitypython/debugutils/load.py
trinitypython/debugutils/timer.py
trinitypython/debugutils/version.py
trinitypython/docutils/__init__.py
trinitypython/docutils/pdf.py
trinitypython/docutils/project.py
trinitypython/docutils/testcase.py
trinitypython/fileutils/__init__.py
trinitypython/fileutils/cleanup.py
trinitypython/fileutils/compare.py
trinitypython/fileutils/compare_dir.py
trinitypython/fileutils/dir_info.py
trinitypython/fileutils/excel.py
trinitypython/fileutils/html_template.py
trinitypython/netutils/__init__.py
trinitypython/netutils/port.py
trinitypython/uiutils/__init__.py
trinitypython/uiutils/menu_based_app.py
trinitypython-0.0.30.dist-info/METADATA
trinitypython-0.0.30.dist-info/WHEEL
trinitypython-0.0.30.dist-info/RECORD
